notcl/__init__.py
notcl/bridge_client.py
notcl/bridge_server.py
notcl/message.py
notcl/msg_classes.py
notcl/tclobj.py
notcl/tcltool.py
notcl/version.py
notcl/apps/__init__.py
notcl/apps/vivado.py
notcl/apps/yosys.py
notcl/tcl/__init__.py
notcl/tcl/notcl.tcl
notcl/tests/__init__.py
notcl/tests/test_bridge.py
notcl/tests/test_custom_tclsh.py
notcl/tests/test_tclobj.py
notcl/tests/test_tclsh.py
notcl-0.3.6.dist-info/licenses/LICENSE
notcl-0.3.6.dist-info/METADATA
notcl-0.3.6.dist-info/WHEEL
notcl-0.3.6.dist-info/top_level.txt
notcl-0.3.6.dist-info/RECORD
