Metadata-Version: 2.4
Name: notcl
Version: 0.3.6
Summary: Replace Tcl scripting with Python
Maintainer-email: Tobias Kaiser <mail@tb-kaiser.de>
License-Expression: Apache-2.0
Project-URL: Homepage, https://github.com/TobiasKaiser/notcl
Project-URL: Documentation, https://notcl.readthedocs.io
Classifier: Programming Language :: Python :: 3
Classifier: Programming Language :: Tcl
Classifier: Topic :: Scientific/Engineering :: Electronic Design Automation (EDA)
Requires-Python: >=3.9
License-File: LICENSE
Dynamic: license-file
